Workbook
Name Slicer_Order_Status: #N/A

Sheet Dashboard
A2: Total Net Revenue | D2: Total Orders | G2: AOV | J2: Cancellation Rate | M2: Revenue Lost
A3: =Analysis!B9 -> 88310 | D3: =Analysis!B10 -> 30 | G3: =Analysis!B11 -> 2943.6667 | J3: =Analysis!C26 -> 0.066666667 | M3: =Analysis!B14 -> 16790
AC35: x`

Sheet Insights
A1: Executive Summary
A5: QuickMart Retail Performance – Jan 2024
A7: Total Net Revenue | E7: =Analysis!B9 -> 88310
A8: Total Orders | E8: =Analysis!B10 -> 30
A9: Average Order Value (AOV) | E9: =Analysis!B11 -> 2943.6667
A10: Cancellation Rate | E10: =Analysis!C26 -> 0.066666667
A11: Revenue Lost (Cancelled + Returned) | E11: =Analysis!B14 -> 16790
A12: Realized Revenue (Delivered Only) | E12: =Analysis!B13 -> 0.80987431
A15: Key Business Insights
A25: Observations

Sheet Analysis
A1: QuickMart Retail Analysis
F2: UNIQUE CITIES | G2: Unique Product Categoies | H2: Store Types | I2: Order Status | J2: Order Types | K2: Discount Levels | L2: Payment_Category
A3: Time period: Jan 2024 | F3: {=_xlfn.UNIQUE(tbl_quickmart[City])} -> Delhi | G3: {=_xlfn.UNIQUE(tbl_quickmart[Product_Category])} -> Electronics | H3: {=_xlfn.UNIQUE(tbl_quickmart[Store_Type])} -> Mall | I3: {=_xlfn.UNIQUE(tbl_quickmart[Order_Status])} -> Delivered | J3: {=_xlfn.UNIQUE(tbl_quickmart[High_Value_Order])} -> Normal | K3: {=_xlfn.UNIQUE(tbl_quickmart[Discount_Level IFS])} -> Low | L3: {=_xlfn.UNIQUE(tbl_quickmart[Payment_Category])} -> Digital
F4: Mumbai | G4: Fashion | H4: Online | I4: Returned | J4: High | K4: NO Discount | L4: Cash
A5: Tools: Power Query + Excel formulas + PivotTables | F5: Bangalore | G5: Grocery | H5: High Street | I5: Cancelled | K5: High
F6: Chennai | G6: Beauty
F7: Kolkata
A8: 1. Revenue Summary
A9: Total Net Revenue | B9: =SUM(tbl_quickmart[Net_Revenue]) -> 88310 | F9: Total Orders | G9: Total Delivered Orders | H9: Total Cancelled Orders
A10: Total Orders | B10: =F10 -> 30 | F10: =COUNTA(tbl_quickmart[Order_ID]) -> 30 | G10: =COUNTIF(tbl_quickmart[Order_Status],Analysis!I3) -> 25 | H10: =COUNTIF(tbl_quickmart[Order_Status],Analysis!I5) -> 2
A11: AOV (Average of Order) | B11: =B9/B10 -> 2943.6667
A12: Delivered Revenue | B12: =SUMIFS(tbl_quickmart[Net_Revenue],tbl_quickmart[Order_Status],Analysis!I3) -> 71520 | F12: 4. Supporting Tables
A13: Realized Revenue % | B13: =B12/B9 -> 0.80987431 | F13: REVENUE PER CITY
A14: Revenue Lost (Cancelled + Returned) | B14: =SUM(SUMIFS(tbl_quickmart[Net_Revenue],tbl_quickmart[Order_Status],Analysis!I5),SUMIFS(tbl_quickmart[Net_Revenue],tbl_quickmart[Order_Status],Analysis!I4)) -> 16790 | F14: CITY | G14: REVENUE | H14: Revenue Contribution %
A15: % Revenue Lost | B15: =B14/B9 -> 0.19012569 | F15: {=_xlfn.UNIQUE(tbl_quickmart[City])} -> Delhi | G15: =SUMIFS(tbl_quickmart[Net_Revenue],tbl_quickmart[City],Analysis!F15) -> 18290 | H15: =G15/$B$9 -> 0.20711131
F16: Mumbai | G16: =SUMIFS(tbl_quickmart[Net_Revenue],tbl_quickmart[City],Analysis!F16) -> 12940 | H16: =G16/$B$9 -> 0.14652927
F17: Bangalore | G17: =SUMIFS(tbl_quickmart[Net_Revenue],tbl_quickmart[City],Analysis!F17) -> 31840 | H17: =G17/$B$9 -> 0.36054807
A18: 2. Performance Breakdown | F18: Chennai | G18: =SUMIFS(tbl_quickmart[Net_Revenue],tbl_quickmart[City],Analysis!F18) -> 11230 | H18: =G18/$B$9 -> 0.12716567
A19: Top City + Revenue | B19: =LARGE(G15:G19,1) -> 31840 | C19: =INDEX(_xlfn.ANCHORARRAY(F15),MATCH(B19,G15:G19,0)) -> Bangalore | F19: Kolkata | G19: =SUMIFS(tbl_quickmart[Net_Revenue],tbl_quickmart[City],Analysis!F19) -> 14010 | H19: =G19/$B$9 -> 0.15864568
A20: Lowest City + Revenue | B20: =MIN(G15:G19) -> 11230 | C20: =INDEX(_xlfn.ANCHORARRAY(F15),MATCH(B20,G15:G19,0)) -> Chennai
A21: Best Category + Revenue | B21: =MAX(G23:G26) -> 47880 | C21: =INDEX(_xlfn.ANCHORARRAY(F23),MATCH(B21,G23:G26,0)) -> Electronics | F21: Revenue Per Category
A22: Best Store Type + Revenue (from pivot totals or SUMIFS table) | B22: =MAX(G30:G32) -> 51235 | C22: =INDEX(_xlfn.ANCHORARRAY(F30),MATCH(B22,G30:G32,0)) -> Mall | F22: Category | G22: Revenue
F23: {=_xlfn.UNIQUE(tbl_quickmart[Product_Category])} -> Electronics | G23: =SUMIFS(tbl_quickmart[Net_Revenue],tbl_quickmart[Product_Category],Analysis!F23) -> 47880
F24: Fashion | G24: =SUMIFS(tbl_quickmart[Net_Revenue],tbl_quickmart[Product_Category],Analysis!F24) -> 25315
A25: 3. Risk / Ops Metrics | F25: Grocery | G25: =SUMIFS(tbl_quickmart[Net_Revenue],tbl_quickmart[Product_Category],Analysis!F25) -> 7440
A26: Cancelled Orders count + % | B26: =COUNTIFS(tbl_quickmart[Order_Status],Analysis!I5) -> 2 | C26: =B26/B10 -> 0.066666667 | F26: Beauty | G26: =SUMIFS(tbl_quickmart[Net_Revenue],tbl_quickmart[Product_Category],Analysis!F26) -> 7675
A27: Returned Orders count + % | B27: =COUNTIFS(tbl_quickmart[Order_Status],Analysis!I4) -> 3 | C27: =B27/B10 -> 0.1
A28: High Value Orders count | B28: =COUNTIFS(tbl_quickmart[High_Value_Order],Analysis!J4) -> 4 | F28: Revenue Per Store Type
A29: High Discount Revenue | B29: =SUMIFS(tbl_quickmart[Net_Revenue],tbl_quickmart[Discount_Level IFS],Analysis!K5) -> 26525 | F29: Store Type | G29: Revenue
F30: {=_xlfn.UNIQUE(tbl_quickmart[Store_Type])} -> Mall | G30: =SUMIFS(tbl_quickmart[Net_Revenue],tbl_quickmart[Store_Type],Analysis!F30) -> 51235
F31: Online | G31: =SUMIFS(tbl_quickmart[Net_Revenue],tbl_quickmart[Store_Type],Analysis!F31) -> 28030
A32: Payment Behavior Analysis | F32: High Street | G32: =SUMIFS(tbl_quickmart[Net_Revenue],tbl_quickmart[Store_Type],Analysis!F32) -> 9045
A33: Net Revenue – Digital | B33: =SUMIFS(tbl_quickmart[Net_Revenue],tbl_quickmart[Payment_Category],Analysis!L3) -> 80870 | C33: =B33/$B$9 -> 0.91575133
A34: Net Revenue – Cash | B34: =SUMIFS(tbl_quickmart[Net_Revenue],tbl_quickmart[Payment_Category],Analysis!L4) -> 7440 | C34: =B34/$B$9 -> 0.084248669

Sheet Pivot_City
A1: Order_Status | B1: (All)
A3: Row Labels | B3: Sum of Net_Revenue
A4: Bangalore | B4: 31840
A5: Delhi | B5: 18290
A6: Kolkata | B6: 14010
A7: Mumbai | B7: 12940
A8: Chennai | B8: 11230
A9: Grand Total | B9: 88310

Sheet Pivot_CategoryStore
A3: Row Labels | B3: Sum of Net_Revenue
A4: Beauty | B4: 7675
A5: Electronics | B5: 47880
A6: Fashion | B6: 25315
A7: Grocery | B7: 7440
A8: Grand Total | B8: 88310

Sheet Data
A1: Order_ID | B1: Order_Date | C1: City | D1: State | E1: Store_Type | F1: Customer_ID | G1: Gender | H1: Age | I1: Product_Category | J1: Product_Name | K1: Quantity | L1: Unit_Price | M1: Discount_% | N1: Payment_Method | O1: Order_Status | P1: Revenue | Q1: Discount_Amount | R1: Net_Revenue | S1: Age_Group | T1: Payment_Category | U1: Order_Flag | V1: High_Value_Order | W1: Discount_Level IFS
A2: 1001 | B2: 45292 | C2: Delhi | D2: Delhi | E2: Mall | F2: C101 | G2: Male | H2: 25 | I2: Electronics | J2: Headphones | K2: 2 | L2: 1500 | M2: 10 | N2: UPI | O2: Delivered | P2: 3000 | Q2: 300 | R2: 2700 | S2: Adult | T2: =IF(tbl_quickmart[[#This Row],[Payment_Method]]="Cash","Cash","Digital") -> Digital | U2: =IF(tbl_quickmart[[#This Row],[Order_Status]]="Delivered",1,0) -> 1 | V2: =IF(tbl_quickmart[[#This Row],[Net_Revenue]]>5000,"High","Normal") -> Normal | W2: {=_xlfn.IFS(tbl_quickmart[[#This Row],[Discount_%]]=0,"NO Discount",AND(tbl_quickmart[[#This Row],[Discount_%]]>0,tbl_quickmart[[#This Row],[Discount_%]]<=10),"Low",tbl_quickmart[[#This Row],[Discount_%]]>10,"High")} -> Low
A3: 1002 | B3: 45293 | C3: Mumbai | D3: Maharashtra | E3: Online | F3: C102 | G3: Female | H3: 32 | I3: Fashion | J3: T-Shirt | K3: 3 | L3: 800 | M3: 5 | N3: Card | O3: Delivered | P3: 2400 | Q3: 120 | R3: 2280 | S3: Adult | T3: =IF(tbl_quickmart[[#This Row],[Payment_Method]]="Cash","Cash","Digital") -> Digital | U3: =IF(tbl_quickmart[[#This Row],[Order_Status]]="Delivered",1,0) -> 1 | V3: =IF(tbl_quickmart[[#This Row],[Net_Revenue]]>5000,"High","Normal") -> Normal | W3: {=_xlfn.IFS(tbl_quickmart[[#This Row],[Discount_%]]=0,"NO Discount",AND(tbl_quickmart[[#This Row],[Discount_%]]>0,tbl_quickmart[[#This Row],[Discount_%]]<=10),"Low",tbl_quickmart[[#This Row],[Discount_%]]>10,"High")} -> Low
A4: 1003 | B4: 45294 | C4: Bangalore | D4: Karnataka | E4: High Street | F4: C103 | G4: Male | H4: 45 | I4: Grocery | J4: Rice Bag | K4: 1 | L4: 1200 | M4: 0 | N4: Cash | O4: Delivered | P4: 1200 | Q4: 0 | R4: 1200 | S4: Senior | T4: =IF(tbl_quickmart[[#This Row],[Payment_Method]]="Cash","Cash","Digital") -> Cash | U4: =IF(tbl_quickmart[[#This Row],[Order_Status]]="Delivered",1,0) -> 1 | V4: =IF(tbl_quickmart[[#This Row],[Net_Revenue]]>5000,"High","Normal") -> Normal | W4: {=_xlfn.IFS(tbl_quickmart[[#This Row],[Discount_%]]=0,"NO Discount",AND(tbl_quickmart[[#This Row],[Discount_%]]>0,tbl_quickmart[[#This Row],[Discount_%]]<=10),"Low",tbl_quickmart[[#This Row],[Discount_%]]>10,"High")} -> NO Discount
A5: 1004 | B5: 45294 | C5: Delhi | D5: Delhi | E5: Online | F5: C104 | G5: Female | H5: 29 | I5: Electronics | J5: Smart Watch | K5: 1 | L5: 5000 | M5: 15 | N5: UPI | O5: Returned | P5: 5000 | Q5: 750 | R5: 4250 | S5: Adult | T5: =IF(tbl_quickmart[[#This Row],[Payment_Method]]="Cash","Cash","Digital") -> Digital | U5: =IF(tbl_quickmart[[#This Row],[Order_Status]]="Delivered",1,0) -> 0 | V5: =IF(tbl_quickmart[[#This Row],[Net_Revenue]]>5000,"High","Normal") -> Normal | W5: {=_xlfn.IFS(tbl_quickmart[[#This Row],[Discount_%]]=0,"NO Discount",AND(tbl_quickmart[[#This Row],[Discount_%]]>0,tbl_quickmart[[#This Row],[Discount_%]]<=10),"Low",tbl_quickmart[[#This Row],[Discount_%]]>10,"High")} -> High
A6: 1005 | B6: 45295 | C6: Chennai | D6: Tamil Nadu | E6: Mall | F6: C105 | G6: Male | H6: 38 | I6: Fashion | J6: Shoes | K6: 2 | L6: 2500 | M6: 20 | N6: Card | O6: Delivered | P6: 5000 | Q6: 1000 | R6: 4000 | S6: Adult | T6: =IF(tbl_quickmart[[#This Row],[Payment_Method]]="Cash","Cash","Digital") -> Digital | U6: =IF(tbl_quickmart[[#This Row],[Order_Status]]="Delivered",1,0) -> 1 | V6: =IF(tbl_quickmart[[#This Row],[Net_Revenue]]>5000,"High","Normal") -> Normal | W6: {=_xlfn.IFS(tbl_quickmart[[#This Row],[Discount_%]]=0,"NO Discount",AND(tbl_quickmart[[#This Row],[Discount_%]]>0,tbl_quickmart[[#This Row],[Discount_%]]<=10),"Low",tbl_quickmart[[#This Row],[Discount_%]]>10,"High")} -> High
A7: 1006 | B7: 45296 | C7: Mumbai | D7: Maharashtra | E7: Online | F7: C106 | G7: Female | H7: 22 | I7: Beauty | J7: Lipstick | K7: 4 | L7: 600 | M7: 5 | N7: Wallet | O7: Cancelled | P7: 2400 | Q7: 120 | R7: 2280 | S7: Young | T7: =IF(tbl_quickmart[[#This Row],[Payment_Method]]="Cash","Cash","Digital") -> Digital | U7: =IF(tbl_quickmart[[#This Row],[Order_Status]]="Delivered",1,0) -> 0 | V7: =IF(tbl_quickmart[[#This Row],[Net_Revenue]]>5000,"High","Normal") -> Normal | W7: {=_xlfn.IFS(tbl_quickmart[[#This Row],[Discount_%]]=0,"NO Discount",AND(tbl_quickmart[[#This Row],[Discount_%]]>0,tbl_quickmart[[#This Row],[Discount_%]]<=10),"Low",tbl_quickmart[[#This Row],[Discount_%]]>10,"High")} -> Low
A8: 1007 | B8: 45297 | C8: Kolkata | D8: West Bengal | E8: High Street | F8: C107 | G8: Male | H8: 30 | I8: Grocery | J8: Cooking Oil | K8: 3 | L8: 180 | M8: 0 | N8: Cash | O8: Delivered | P8: 540 | Q8: 0 | R8: 540 | S8: Adult | T8: =IF(tbl_quickmart[[#This Row],[Payment_Method]]="Cash","Cash","Digital") -> Cash | U8: =IF(tbl_quickmart[[#This Row],[Order_Status]]="Delivered",1,0) -> 1 | V8: =IF(tbl_quickmart[[#This Row],[Net_Revenue]]>5000,"High","Normal") -> Normal | W8: {=_xlfn.IFS(tbl_quickmart[[#This Row],[Discount_%]]=0,"NO Discount",AND(tbl_quickmart[[#This Row],[Discount_%]]>0,tbl_quickmart[[#This Row],[Discount_%]]<=10),"Low",tbl_quickmart[[#This Row],[Discount_%]]>10,"High")} -> NO Discount
A9: 1008 | B9: 45298 | C9: Delhi | D9: Delhi | E9: Mall | F9: C108 | G9: Female | H9: 41 | I9: Electronics | J9: Speaker | K9: 1 | L9: 3500 | M9: 10 | N9: UPI | O9: Delivered | P9: 3500 | Q9: 350 | R9: 3150 | S9: Senior | T9: =IF(tbl_quickmart[[#This Row],[Payment_Method]]="Cash","Cash","Digital") -> Digital | U9: =IF(tbl_quickmart[[#This Row],[Order_Status]]="Delivered",1,0) -> 1 | V9: =IF(tbl_quickmart[[#This Row],[Net_Revenue]]>5000,"High","Normal") -> Normal | W9: {=_xlfn.IFS(tbl_quickmart[[#This Row],[Discount_%]]=0,"NO Discount",AND(tbl_quickmart[[#This Row],[Discount_%]]>0,tbl_quickmart[[#This Row],[Discount_%]]<=10),"Low",tbl_quickmart[[#This Row],[Discount_%]]>10,"High")} -> Low
A10: 1009 | B10: 45299 | C10: Bangalore | D10: Karnataka | E10: Online | F10: C109 | G10: Male | H10: 27 | I10: Fashion | J10: Jeans | K10: 2 | L10: 2200 | M10: 5 | N10: Card | O10: Delivered | P10: 4400 | Q10: 220 | R10: 4180 | S10: Adult | T10: =IF(tbl_quickmart[[#This Row],[Payment_Method]]="Cash","Cash","Digital") -> Digital | U10: =IF(tbl_quickmart[[#This Row],[Order_Status]]="Delivered",1,0) -> 1 | V10: =IF(tbl_quickmart[[#This Row],[Net_Revenue]]>5000,"High","Normal") -> Normal | W10: {=_xlfn.IFS(tbl_quickmart[[#This Row],[Discount_%]]=0,"NO Discount",AND(tbl_quickmart[[#This Row],[Discount_%]]>0,tbl_quickmart[[#This Row],[Discount_%]]<=10),"Low",tbl_quickmart[[#This Row],[Discount_%]]>10,"High")} -> Low
A11: 1010 | B11: 45300 | C11: Chennai | D11: Tamil Nadu | E11: Mall | F11: C110 | G11: Female | H11: 35 | I11: Grocery | J11: Wheat Flour | K11: 5 | L11: 450 | M11: 0 | N11: Cash | O11: Delivered | P11: 2250 | Q11: 0 | R11: 2250 | S11: Adult | T11: =IF(tbl_quickmart[[#This Row],[Payment_Method]]="Cash","Cash","Digital") -> Cash | U11: =IF(tbl_quickmart[[#This Row],[Order_Status]]="Delivered",1,0) -> 1 | V11: =IF(tbl_quickmart[[#This Row],[Net_Revenue]]>5000,"High","Normal") -> Normal | W11: {=_xlfn.IFS(tbl_quickmart[[#This Row],[Discount_%]]=0,"NO Discount",AND(tbl_quickmart[[#This Row],[Discount_%]]>0,tbl_quickmart[[#This Row],[Discount_%]]<=10),"Low",tbl_quickmart[[#This Row],[Discount_%]]>10,"High")} -> NO Discount
A12: 1011 | B12: 45301 | C12: Mumbai | D12: Maharashtra | E12: High Street | F12: C111 | G12: Male | H12: 28 | I12: Electronics | J12: Power Bank | K12: 3 | L12: 1200 | M12: 10 | N12: UPI | O12: Delivered | P12: 3600 | Q12: 360 | R12: 3240 | S12: Adult | T12: =IF(tbl_quickmart[[#This Row],[Payment_Method]]="Cash","Cash","Digital") -> Digital | U12: =IF(tbl_quickmart[[#This Row],[Order_Status]]="Delivered",1,0) -> 1 | V12: =IF(tbl_quickmart[[#This Row],[Net_Revenue]]>5000,"High","Normal") -> Normal | W12: {=_xlfn.IFS(tbl_quickmart[[#This Row],[Discount_%]]=0,"NO Discount",AND(tbl_quickmart[[#This Row],[Discount_%]]>0,tbl_quickmart[[#This Row],[Discount_%]]<=10),"Low",tbl_quickmart[[#This Row],[Discount_%]]>10,"High")} -> Low
A13: 1012 | B13: 45302 | C13: Kolkata | D13: West Bengal | E13: Online | F13: C112 | G13: Female | H13: 24 | I13: Beauty | J13: Face Wash | K13: 2 | L13: 300 | M13: 5 | N13: Wallet | O13: Delivered | P13: 600 | Q13: 30 | R13: 570 | S13: Young | T13: =IF(tbl_quickmart[[#This Row],[Payment_Method]]="Cash","Cash","Digital") -> Digital | U13: =IF(tbl_quickmart[[#This Row],[Order_Status]]="Delivered",1,0) -> 1 | V13: =IF(tbl_quickmart[[#This Row],[Net_Revenue]]>5000,"High","Normal") -> Normal | W13: {=_xlfn.IFS(tbl_quickmart[[#This Row],[Discount_%]]=0,"NO Discount",AND(tbl_quickmart[[#This Row],[Discount_%]]>0,tbl_quickmart[[#This Row],[Discount_%]]<=10),"Low",tbl_quickmart[[#This Row],[Discount_%]]>10,"High")} -> Low
... A31: 1030 | B31: 45320 | C31: Chennai | D31: Tamil Nadu | E31: High Street | F31: C130 | G31: Female | H31: 30 | I31: Grocery | J31: Spices | K31: 4 | L31: 250 | M31: 0 | N31: Cash | O31: Delivered | P31: 1000 | Q31: 0 | R31: 1000 | S31: Adult | T31: =IF(tbl_quickmart[[#This Row],[Payment_Method]]="Cash","Cash","Digital") -> Cash | U31: =IF(tbl_quickmart[[#This Row],[Order_Status]]="Delivered",1,0) -> 1 | V31: =IF(tbl_quickmart[[#This Row],[Net_Revenue]]>5000,"High","Normal") -> Normal | W31: {=_xlfn.IFS(tbl_quickmart[[#This Row],[Discount_%]]=0,"NO Discount",AND(tbl_quickmart[[#This Row],[Discount_%]]>0,tbl_quickmart[[#This Row],[Discount_%]]<=10),"Low",tbl_quickmart[[#This Row],[Discount_%]]>10,"High")} -> NO Discount

Sheet Sheet1
A1: Column1
A2: Order_ID,Order_Date,City,State,Store_Type,Customer_ID,Gender,Age,Product_Category,Product_Name,Quantity,Unit_Price,Discount_%,Payment_Method,Order_Status
A3: 1001,01-01-2024,Delhi,Delhi,Mall,C101,Male,25,Electronics,Headphones,2,1500,10,UPI,Delivered
A4: 1002,02-01-2024,Mumbai,Maharashtra,Online,C102,Female,32,Fashion,T-Shirt,3,800,5,Card,Delivered
A5: 1003,03-01-2024,Bangalore,Karnataka,High Street,C103,Male,45,Grocery,Rice Bag,1,1200,0,Cash,Delivered
A6: 1004,03-01-2024,Delhi,Delhi,Online,C104,Female,29,Electronics,Smart Watch,1,5000,15,UPI,Returned
A7: 1005,04-01-2024,Chennai,Tamil Nadu,Mall,C105,Male,38,Fashion,Shoes,2,2500,20,Card,Delivered
A8: 1006,05-01-2024,Mumbai,Maharashtra,Online,C106,Female,22,Beauty,Lipstick,4,600,5,Wallet,Cancelled
A9: 1007,06-01-2024,Kolkata,West Bengal,High Street,C107,Male,30,Grocery,Cooking Oil,3,180,0,Cash,Delivered
A10: 1008,07-01-2024,Delhi,Delhi,Mall,C108,Female,41,Electronics,Speaker,1,3500,10,UPI,Delivered
A11: 1009,08-01-2024,Bangalore,Karnataka,Online,C109,Male,27,Fashion,Jeans,2,2200,5,Card,Delivered
A12: 1010,09-01-2024,Chennai,Tamil Nadu,Mall,C110,Female,35,Grocery,Wheat Flour,5,450,0,Cash,Delivered
... A32: 1030,29-01-2024,Chennai,Tamil Nadu,High Street,C130,Female,30,Grocery,Spices,4,250,0,Cash,Delivered
